sqlalchemy_altibase/__init__.py
sqlalchemy_altibase/base.py
sqlalchemy_altibase/pyodbc.py
sqlalchemy_altibase/requirements.py
sqlalchemy_altibase-1.0.12.dev0.dist-info/METADATA
sqlalchemy_altibase-1.0.12.dev0.dist-info/WHEEL
sqlalchemy_altibase-1.0.12.dev0.dist-info/entry_points.txt
sqlalchemy_altibase-1.0.12.dev0.dist-info/top_level.txt
sqlalchemy_altibase-1.0.12.dev0.dist-info/RECORD
