Metadata-Version: 2.1
Name: sqlalchemy-altibase
Version: 1.0.12.dev0
Summary: Altibase for SQLAlchemy
Author-email: DataX <datax@lguplus.co.kr>
License: MIT
Project-URL: Source Code, https://github.com/LGUPLUS-IPTV-MSA/sqlalchemy-altibase
Keywords: SQLAlchemy Altibase
Classifier: Development Status :: 2 - Pre-Alpha
Classifier: Intended Audience :: Developers
Classifier: License :: OSI Approved :: MIT License
Classifier: Programming Language :: Python
Classifier: Programming Language :: Python :: 3
Classifier: Programming Language :: Python :: Implementation :: CPython
Classifier: Topic :: Database :: Front-Ends
Classifier: Operating System :: OS Independent
Requires-Dist: odbcinst
Requires-Dist: pyodbc
Requires-Dist: sqlalchemy <2,>=1.3.24
Provides-Extra: lint
Requires-Dist: black ; extra == 'lint'
Requires-Dist: flake8 ; extra == 'lint'
Requires-Dist: mypy ; extra == 'lint'
Requires-Dist: isort ; extra == 'lint'
Requires-Dist: pre-commit ; extra == 'lint'
Provides-Extra: test
Requires-Dist: pytest ; extra == 'test'
Requires-Dist: pytest-cov[all] ; extra == 'test'
